grpc_robot/__init__.py
grpc_robot/dmi_robot.py
grpc_robot/grpc_robot.py
grpc_robot/voltha_robot.py
grpc_robot/services/__init__.py
grpc_robot/services/service.py
grpc_robot/services/dmi/__init__.py
grpc_robot/services/dmi/dmi_0_10_1/__init__.py
grpc_robot/services/dmi/dmi_0_10_1/dmi.json
grpc_robot/services/dmi/dmi_0_10_2/__init__.py
grpc_robot/services/dmi/dmi_0_10_2/dmi.json
grpc_robot/services/dmi/dmi_0_12_0/__init__.py
grpc_robot/services/dmi/dmi_0_12_0/dmi.json
grpc_robot/services/dmi/dmi_0_9_1/__init__.py
grpc_robot/services/dmi/dmi_0_9_1/dmi.json
grpc_robot/services/dmi/dmi_0_9_1/hw_events_mgmt_service.py
grpc_robot/services/dmi/dmi_0_9_1/hw_management_service.py
grpc_robot/services/dmi/dmi_0_9_1/hw_metrics_mgmt_service.py
grpc_robot/services/dmi/dmi_0_9_1/sw_management_service.py
grpc_robot/services/dmi/dmi_0_9_2/__init__.py
grpc_robot/services/dmi/dmi_0_9_2/dmi.json
grpc_robot/services/dmi/dmi_0_9_2/hw_management_service.py
grpc_robot/services/dmi/dmi_0_9_3/__init__.py
grpc_robot/services/dmi/dmi_0_9_3/dmi.json
grpc_robot/services/dmi/dmi_0_9_4/__init__.py
grpc_robot/services/dmi/dmi_0_9_4/dmi.json
grpc_robot/services/dmi/dmi_0_9_4/hw_management_service.py
grpc_robot/services/dmi/dmi_0_9_5/__init__.py
grpc_robot/services/dmi/dmi_0_9_5/dmi.json
grpc_robot/services/dmi/dmi_0_9_5/sw_management_service.py
grpc_robot/services/dmi/dmi_0_9_6/__init__.py
grpc_robot/services/dmi/dmi_0_9_6/dmi.json
grpc_robot/services/dmi/dmi_0_9_8/__init__.py
grpc_robot/services/dmi/dmi_0_9_8/dmi.json
grpc_robot/services/dmi/dmi_0_9_8/sw_management_service.py
grpc_robot/services/dmi/dmi_0_9_9/__init__.py
grpc_robot/services/dmi/dmi_0_9_9/dmi.json
grpc_robot/services/dmi/dmi_1_0_0/__init__.py
grpc_robot/services/dmi/dmi_1_0_0/dmi.json
grpc_robot/services/dmi/dmi_1_0_0/hw_events_mgmt_service.py
grpc_robot/services/dmi/dmi_1_0_0/hw_management_service.py
grpc_robot/services/dmi/dmi_1_0_0/hw_metrics_mgmt_service.py
grpc_robot/services/dmi/dmi_1_13_0/__init__.py
grpc_robot-2.11.0.dist-info/LICENSE
grpc_robot-2.11.0.dist-info/METADATA
grpc_robot-2.11.0.dist-info/WHEEL
grpc_robot-2.11.0.dist-info/entry_points.txt
grpc_robot-2.11.0.dist-info/top_level.txt
grpc_robot-2.11.0.dist-info/RECORD
