Metadata-Version: 2.1
Name: grpc-robot
Version: 2.11.0
Summary: Package for sending/recieving messages to/from a gRPC server.
License: Copyright 2020-present Open Networking Foundation
Classifier: Programming Language :: Python :: 3
Classifier: Operating System :: OS Independent
Requires-Python: >=3.6
License-File: LICENSE
Requires-Dist: six
Requires-Dist: robotframework >=3.1.2
Requires-Dist: grpcio
Requires-Dist: decorator
Requires-Dist: attrs
Requires-Dist: parsy
Requires-Dist: device-management-interface >=0.9.1
Requires-Dist: voltha-protos >=4.0.13
